pyvenus/__init__.py
pyvenus/connection.py
pyvenus/data_types.py
pyvenus/helpers.py
pyvenus/resources.py
pyvenus/scripts.py
pyvenus/HSL/HSLremote.hsl
pyvenus/HSL/HSLremote.stp
pyvenus/HSL/HSLExtensions/Array.chm
pyvenus/HSL/HSLExtensions/Array.chw
pyvenus/HSL/HSLExtensions/Array.hsl
pyvenus/HSL/HSLExtensions/Array.stp
pyvenus/HSL/HSLExtensions/Array2D.chm
pyvenus/HSL/HSLExtensions/Array2D.hsl
pyvenus/HSL/HSLExtensions/Array2D.stp
pyvenus/HSL/HSLExtensions/Array3D.chm
pyvenus/HSL/HSLExtensions/Array3D.hsl
pyvenus/HSL/HSLExtensions/Array3D.stp
pyvenus/HSL/HSLExtensions/Core.chm
pyvenus/HSL/HSLExtensions/Core.hsl
pyvenus/HSL/HSLExtensions/Core.stp
pyvenus/HSL/HSLExtensions/Dictionary.chm
pyvenus/HSL/HSLExtensions/Dictionary.hsl
pyvenus/HSL/HSLExtensions/Dictionary.stp
pyvenus/HSL/HSLExtensions/Directory.chm
pyvenus/HSL/HSLExtensions/Directory.chw
pyvenus/HSL/HSLExtensions/Directory.hsl
pyvenus/HSL/HSLExtensions/Directory.stp
pyvenus/HSL/HSLExtensions/Drive.chm
pyvenus/HSL/HSLExtensions/Drive.hsl
pyvenus/HSL/HSLExtensions/Drive.stp
pyvenus/HSL/HSLExtensions/File.chm
pyvenus/HSL/HSLExtensions/File.chw
pyvenus/HSL/HSLExtensions/File.hsl
pyvenus/HSL/HSLExtensions/File.stp
pyvenus/HSL/HSLExtensions/Framework.chm
pyvenus/HSL/HSLExtensions/Framework.hsl
pyvenus/HSL/HSLExtensions/Framework.stp
pyvenus/HSL/HSLExtensions/Pipetting.chm
pyvenus/HSL/HSLExtensions/Pipetting.hsl
pyvenus/HSL/HSLExtensions/Pipetting.stp
pyvenus/HSL/HSLExtensions/Sequence.chm
pyvenus/HSL/HSLExtensions/Sequence.chw
pyvenus/HSL/HSLExtensions/Sequence.hsl
pyvenus/HSL/HSLExtensions/Sequence.stp
pyvenus/HSL/HSLExtensions/SequenceArray2D.chm
pyvenus/HSL/HSLExtensions/SequenceArray2D.hsl
pyvenus/HSL/HSLExtensions/SequenceArray2D.stp
pyvenus/HSL/HSLExtensions/String.chm
pyvenus/HSL/HSLExtensions/String.hsl
pyvenus/HSL/HSLExtensions/String.stp
pyvenus/HSL/HSLExtensions/Venus.chm
pyvenus/HSL/HSLExtensions/Venus.hsl
pyvenus/HSL/HSLExtensions/Venus.stp
pyvenus/HSL/HSLExtensions/Windows.chm
pyvenus-1.1.1.dist-info/COPYING
pyvenus-1.1.1.dist-info/COPYING.LESSER
pyvenus-1.1.1.dist-info/METADATA
pyvenus-1.1.1.dist-info/WHEEL
pyvenus-1.1.1.dist-info/entry_points.txt
pyvenus-1.1.1.dist-info/top_level.txt
pyvenus-1.1.1.dist-info/RECORD
