Metadata-Version: 2.1
Name: pyvenus
Version: 1.1.1
Summary: A Python interface to the Venus environment, used to program Hamilton liquid handlers
Home-page: https://github.com/sniprbiome/pyvenus
Project-URL: Bug Tracker, https://github.com/sniprbiome/pyvenus/issues
Project-URL: Changelog, https://github.com/sniprbiome/pyvenus/releases/
Classifier: Programming Language :: Python :: 3
Classifier: License :: OSI Approved :: GNU Lesser General Public License v3 (LGPLv3)
Requires-Python: >=3.8
License-File: COPYING
License-File: COPYING.LESSER
Requires-Dist: pandas
Requires-Dist: jinja2
Requires-Dist: pyodbc
Requires-Dist: openpyxl
